LICENSE
MANIFEST.in
setup.cfg
setup.py
versioneer.py
buildmatrix/__init__.py
buildmatrix/_version.py
buildmatrix/cli.py
buildmatrix.egg-info/PKG-INFO
buildmatrix.egg-info/SOURCES.txt
buildmatrix.egg-info/dependency_links.txt
buildmatrix.egg-info/entry_points.txt
buildmatrix.egg-info/top_level.txt