Metadata-Version: 1.0
Name: buildmatrix
Version: 0.1.0
Summary: Build a matrix of conda packages
Home-page: http://github.com/ericdill/buildmatrix
Author: Eric Dill
Author-email: thedizzle@gmail.com
License: BSD 3-Clause
Platform: Cross platform (Linux
Platform: Mac OSX
Platform: Windows)
